fastblocks/.pre-commit-config.yaml
fastblocks/Procfile.tmpl
fastblocks/__init__.py
fastblocks/__main__.py
fastblocks/_events_integration.py
fastblocks/_health_integration.py
fastblocks/_validation_integration.py
fastblocks/_workflows_integration.py
fastblocks/applications.py
fastblocks/caching.py
fastblocks/cli.py
fastblocks/decorators.py
fastblocks/exceptions.py
fastblocks/htmx.py
fastblocks/initializers.py
fastblocks/main.py
fastblocks/main.py.tmpl
fastblocks/middleware.py
fastblocks/pyproject.toml.tmpl
fastblocks/actions/README.md
fastblocks/actions/__init__.py
fastblocks/actions/gather/README.md
fastblocks/actions/gather/__init__.py
fastblocks/actions/gather/application.py
fastblocks/actions/gather/components.py
fastblocks/actions/gather/middleware.py
fastblocks/actions/gather/models.py
fastblocks/actions/gather/routes.py
fastblocks/actions/gather/strategies.py
fastblocks/actions/gather/templates.py
fastblocks/actions/minify/README.md
fastblocks/actions/minify/__init__.py
fastblocks/actions/query/README.md
fastblocks/actions/query/__init__.py
fastblocks/actions/query/parser.py
fastblocks/actions/sync/README.md
fastblocks/actions/sync/__init__.py
fastblocks/actions/sync/cache.py
fastblocks/actions/sync/settings.py
fastblocks/actions/sync/static.py
fastblocks/actions/sync/strategies.py
fastblocks/actions/sync/templates.py
fastblocks/adapters/README.md
fastblocks/adapters/__init__.py
fastblocks/adapters/admin/README.md
fastblocks/adapters/admin/__init__.py
fastblocks/adapters/admin/_base.py
fastblocks/adapters/admin/sqladmin.py
fastblocks/adapters/admin/_templates/bootstrap/sqladmin/create.html
fastblocks/adapters/admin/_templates/bootstrap/sqladmin/edit.html
fastblocks/adapters/admin/_templates/bootstrap/sqladmin/layout.html
fastblocks/adapters/admin/_templates/bootstrap/sqladmin/login.html
fastblocks/adapters/admin/_templates/bootstrap/sqladmin/blocks/display_menu.html
fastblocks/adapters/admin/_templates/bootstrap/sqladmin/blocks/menu_category.html
fastblocks-0.18.7.dist-info/METADATA
fastblocks-0.18.7.dist-info/WHEEL
fastblocks-0.18.7.dist-info/licenses/LICENSE
fastblocks-0.18.7.dist-info/RECORD
