Metadata-Version: 2.4
Name: fastblocks
Version: 0.18.7
Summary: Starlette based app for the rapid delivery of HTMX/Jinja template blocks
Author-email: lesleslie <les@wedgwoodwebworks.com>
Maintainer-email: lesleslie <les@wedgwoodwebworks.com>
License: BSD-3-Clause
License-File: LICENSE
Keywords: htmx,httpx,jinja,pydantic,redis,sqladmin,sqlalchemy,sqlmodel,starlette
Classifier: Development Status :: 3 - Alpha
Classifier: Framework :: AsyncIO
Classifier: Framework :: Pydantic
Classifier: Framework :: Pydantic :: 2
Classifier: License :: OSI Approved :: BSD License
Classifier: Operating System :: OS Independent
Classifier: Programming Language :: Python
Classifier: Programming Language :: Python :: 3 :: Only
Classifier: Programming Language :: Python :: 3.13
Classifier: Topic :: Internet :: WWW/HTTP :: Dynamic Content
Classifier: Topic :: Software Development :: Libraries :: Application Frameworks
Classifier: Typing :: Typed
Requires-Python: >=3.13
Requires-Dist: anyio>=4.11.0
Requires-Dist: brotli-asgi>=1.5.0
Requires-Dist: granian[reload]>=2.6.0
Requires-Dist: htmy[lxml]>=0.9.0
Requires-Dist: mcp-common>=0.3.3
Requires-Dist: minify-html>=0.18.1
Requires-Dist: pydantic>=2.12.4
Requires-Dist: pyfiglet>=1.0.4
Requires-Dist: rcssmin>=1.2.2
Requires-Dist: rjsmin>=1.2.5
Requires-Dist: secure>=1.0.1
Requires-Dist: starception>=1.2.1
Requires-Dist: starlette-async-jinja>=1.13.3
Requires-Dist: starlette-csrf>=3.0.0
Requires-Dist: starlette>=0.50.0
Requires-Dist: typer>=0.20.0
Requires-Dist: uvicorn>=0.38.0
